coptrs-0.1.1.dist-info/METADATA
coptrs-0.1.1.dist-info/WHEEL
coptrs-0.1.1.dist-info/licenses/LICENSE
coptrs/__init__.py
coptrs/coptrs.cpython-38-i386-linux-gnu.so
coptrs-0.1.1.dist-info/RECORD
